pips/__init__.py
pips/pips.py
pips_tool-0.4.dist-info/METADATA
pips_tool-0.4.dist-info/WHEEL
pips_tool-0.4.dist-info/entry_points.txt
pips_tool-0.4.dist-info/top_level.txt
pips_tool-0.4.dist-info/RECORD
