Metadata-Version: 2.1
Name: pips-tool
Version: 0.4
Summary: pip wrapper for new requirements handling
Home-page: https://github.com/jboegeholz/pips-tool
Author: Joern Boegeholz
Author-email: boegeholz.joern@gmail.com
License: MIT
Platform: UNKNOWN
Requires-Dist: pip
Requires-Dist: pipdeptree
